moveit2_commander/__init__.py
moveit2_commander/cli.py
moveit2_commander/moveit2_commander.py
moveit2_commander/core/__init__.py
moveit2_commander/core/apply_planning_scene_service_manager.py
moveit2_commander/core/catesian_path_service_manager.py
moveit2_commander/core/execute_trajectory_service_manager.py
moveit2_commander/core/fk_service_manager.py
moveit2_commander/core/get_planning_scene_service_manager.py
moveit2_commander/core/ik_service_manager.py
moveit2_commander/core/kinematic_path_service_manager.py
moveit2_commander/core/modules.py
moveit2_commander/core/service_manager.py
moveit2_commander-0.1.2.dist-info/licenses/AUTHORS.rst
moveit2_commander-0.1.2.dist-info/licenses/LICENSE
moveit2_commander-0.1.2.dist-info/METADATA
moveit2_commander-0.1.2.dist-info/WHEEL
moveit2_commander-0.1.2.dist-info/top_level.txt
moveit2_commander-0.1.2.dist-info/RECORD
