Metadata-Version: 2.4
Name: moveit2_commander
Version: 0.1.2
Summary: package for controlling moveit2 services
Author-email: SoYu42 <dg.min0246@gmail.com>
Maintainer-email: SoYu42 <dg.min0246@gmail.com>
License: MIT license
Project-URL: bugs, https://github.com/{{ cookiecutter.github_username }}/{{ cookiecutter.project_slug }}/issues
Project-URL: changelog, https://github.com/{{ cookiecutter.github_username }}/{{ cookiecutter.project_slug }}/blob/master/changelog.md
Project-URL: homepage, https://github.com/{{ cookiecutter.github_username }}/{{ cookiecutter.project_slug }}
License-File: LICENSE
License-File: AUTHORS.rst
Requires-Dist: typer
Provides-Extra: dev
Requires-Dist: coverage; extra == "dev"
Requires-Dist: mypy; extra == "dev"
Requires-Dist: pytest; extra == "dev"
Requires-Dist: ruff; extra == "dev"
Dynamic: license-file
